setup.cfg
setup.py
doxhund/__init__.py
doxhund.egg-info/PKG-INFO
doxhund.egg-info/SOURCES.txt
doxhund.egg-info/dependency_links.txt
doxhund.egg-info/not-zip-safe
doxhund.egg-info/requires.txt
doxhund.egg-info/top_level.txt
doxhund/domain/__init__.py
doxhund/domain/blacklists.py
doxhund/domain/check.py
doxhund/domain/domaintools.py
doxhund/domain/lookup.py
doxhund/extract/__init__.py
doxhund/extract/extractor.py
doxhund/extract/html.py
doxhund/social/__init__.py
doxhund/social/activity.py
doxhund/social/providers.py