Metadata-Version: 1.1
Name: doxhund
Version: 0.2.19
Summary: Post-truth era news article metadata service.
Home-page: https://github.com/psolbach/doxhund
Author: Paul Solbach
Author-email: p@psolbach.com
License: MIT
Keywords: scraping,metadata,news article
Platform: UNKNOWN
Classifier: Programming Language :: Python :: 3.5
Classifier: Topic :: Internet :: WWW/HTTP
Classifier: Development Status :: 3 - Alpha
Classifier: License :: OSI Approved :: MIT License
Classifier: Intended Audience :: Developers
Classifier: Operating System :: POSIX :: Linux
Classifier: Environment :: Web Environment
